myneuralnet/__init__.py
myneuralnet/activations.py
myneuralnet/layers.py
myneuralnet/loss.py
myneuralnet/network.py
myneuralnet-0.1.0.dist-info/licenses/LICENSE
myneuralnet-0.1.0.dist-info/METADATA
myneuralnet-0.1.0.dist-info/WHEEL
myneuralnet-0.1.0.dist-info/top_level.txt
myneuralnet-0.1.0.dist-info/RECORD
